odoo/addons/loyalty_mass_mailing/README.rst
odoo/addons/loyalty_mass_mailing/__init__.py
odoo/addons/loyalty_mass_mailing/__manifest__.py
odoo/addons/loyalty_mass_mailing/i18n/es.po
odoo/addons/loyalty_mass_mailing/i18n/it.po
odoo/addons/loyalty_mass_mailing/i18n/loyalty_mass_mailing.pot
odoo/addons/loyalty_mass_mailing/models/__init__.py
odoo/addons/loyalty_mass_mailing/models/loyalty_program.py
odoo/addons/loyalty_mass_mailing/models/mailing_mailing.py
odoo/addons/loyalty_mass_mailing/readme/CONTRIBUTORS.md
odoo/addons/loyalty_mass_mailing/readme/DESCRIPTION.md
odoo/addons/loyalty_mass_mailing/static/description/icon.png
odoo/addons/loyalty_mass_mailing/static/description/index.html
odoo/addons/loyalty_mass_mailing/tests/__init__.py
odoo/addons/loyalty_mass_mailing/tests/test_loyalty_mass_mailing.py
odoo/addons/loyalty_mass_mailing/views/loyalty_program_view.xml
odoo/addons/loyalty_mass_mailing/views/mailing_mailing_view.xml
odoo_addon_loyalty_mass_mailing-18.0.1.0.0.2.dist-info/METADATA
odoo_addon_loyalty_mass_mailing-18.0.1.0.0.2.dist-info/WHEEL
odoo_addon_loyalty_mass_mailing-18.0.1.0.0.2.dist-info/top_level.txt
odoo_addon_loyalty_mass_mailing-18.0.1.0.0.2.dist-info/RECORD
